simplesort/__init__.py
simplesort/mergesort.py
simplesort-0.1.1.dist-info/licenses/LICENSE
simplesort-0.1.1.dist-info/METADATA
simplesort-0.1.1.dist-info/WHEEL
simplesort-0.1.1.dist-info/top_level.txt
simplesort-0.1.1.dist-info/RECORD
