Metadata-Version: 2.4
Name: simplesort
Version: 0.1.1
Summary: A simple Python library containing a merge sort implementation.
Author-email: Brandon G <vntmln1@gmail.com>
Project-URL: Homepage, https://github.com/bebrowq/simplesort
Project-URL: Issues, https://github.com/bebrowq/simplesort/issues
Keywords: sort,merge sort,algorithm
Classifier: Programming Language :: Python :: 3
Classifier: License :: OSI Approved :: MIT License
Classifier: Operating System :: OS Independent
Classifier: Intended Audience :: Developers
Classifier: Topic :: Software Development :: Libraries :: Python Modules
Requires-Python: >=3.7
License-File: LICENSE
Dynamic: license-file
